{"player_x":168,"player_y":210,"walls":[{"x":102,"y":114,"width":30,"height":693,"type":"metal"},{"x":105,"y":120,"width":216,"height":33,"type":"metal"},{"x":312,"y":315,"width":36,"height":486,"type":"metal"},{"x":309,"y":285,"width":621,"height":39,"type":"metal"},{"x":306,"y":138,"width":39,"height":144,"type":"metal","switch":"0xffcccc"},{"x":93,"y":516,"width":282,"height":3,"type":"wood"},{"x":36,"y":768,"width":639,"height":36,"type":"metal"},{"x":522,"y":144,"width":36,"height":144,"type":"wood"},{"x":735,"y":159,"width":30,"height":126,"type":"wood"},{"x":477,"y":447,"width":840,"height":18,"type":"metal"},{"x":1143,"y":135,"width":75,"height":177,"type":"metal"},{"x":915,"y":291,"width":312,"height":42,"type":"wood"},{"x":1134,"y":279,"width":315,"height":42,"type":"metal"},{"x":1269,"y":432,"width":45,"height":510,"type":"metal"},{"x":318,"y":96,"width":906,"height":42,"type":"metal"},{"x":1413,"y":258,"width":45,"height":684,"type":"metal"},{"x":1269,"y":912,"width":204,"height":66,"type":"metal"},{"x":1251,"y":693,"width":234,"height":36,"type":"metal","switch":"0x0000ff"},{"x":660,"y":303,"width":33,"height":183,"type":"wood"},{"x":639,"y":429,"width":69,"height":348,"type":"metal"}],"spawners":[{"x":1038,"y":648,"delay":"12000"},{"x":45,"y":606,"delay":"8000"},{"x":807,"y":387,"delay":"6000"},{"x":1383,"y":582,"delay":"17000"}],"switches":[{"x":210,"y":702,"key":"0xffcccc"},{"x":510,"y":534,"key":"0x0000ff"}],"end_x":1371,"end_y":861}